<?xml version='1.0' encoding='utf-8'?>
<mujoco model="floors">
  <compiler angle="radian" autolimits="true" />
  <option gravity="0 0 -9.81" />
  <include file="./Lite3.xml"/>
  <worldbody>
    <light name="key" pos="18 -12 28" dir="-0.45 0.3 -1" directional="true" diffuse="0.95 0.92 0.88" specular="0.2 0.2 0.2" castshadow="true" />
    <light name="fill" pos="-20 16 18" dir="0.55 -0.35 -1" directional="true" diffuse="0.45 0.5 0.6" specular="0.05 0.05 0.05" castshadow="false" intensity="80.8" />
    <light name="rim" pos="0 24 12" dir="0 -1 -0.35" directional="true" diffuse="0.28 0.3 0.34" specular="0.03 0.03 0.03" castshadow="false" intensity="80.8" />
    <geom name="Floor_001_001" type="box" pos="-5.24413919 1.6248012e-07 1.01550075e-08" quat="1 0 0 0" size="5.27315547 4.88068702 0.0681491077" rgba="0.800007463 0.783353686 0.451678276 1" />
    <geom name="Floor_001_002" type="box" pos="-5.9357686 2.86484337 0.284178615" quat="0.715183735 0.651365757 0.21691376 0.131085277" size="0.322500612 0.200877296 0.108130456" rgba="0.234806538 0.623373747 0.34515056 1" />
    <geom name="Floor_001_003" type="box" pos="-6.09798574 0.935682058 0.400731593" quat="0.517895639 -0.497705758 -0.523242056 0.458574772" size="0.31932986 0.310097047 0.246831029" rgba="0.0725907683 0.623321593 0.510010302 1" />
    <geom name="Floor_001_004" type="box" pos="-3.65949678 4.18221617 0.187719703" quat="0.0498071387 -0.868952274 -0.491238534 0.0335552134" size="0.253121072 0.202582467 0.171693781" rgba="0.505277038 0.0545665249 0.173904255 1" />
    <geom name="Floor_001_005" type="box" pos="-7.38889217 -0.801689684 0.247030139" quat="0.701552451 0.684699178 -0.137132227 -0.142147601" size="0.325696723 0.259041485 0.208907059" rgba="0.505277038 0.0545665249 0.173904255 1" />
    <geom name="Floor_001_006" type="box" pos="-1.23759604 2.30538344 0.345464706" quat="0.651993632 0.738462985 0.135971248 0.105302021" size="0.280927144 0.231167112 0.136981426" rgba="0.423859417 0.601138115 0.12627995 1" />
    <geom name="Floor_001_007" type="box" pos="-2.12378526 -2.58962822 0.347635716" quat="0.55181849 0.543707728 -0.396509558 -0.492603868" size="0.324144015 0.314250318 0.124871474" rgba="0.0725907683 0.623321593 0.510010302 1" />
    <geom name="Floor_001_008" type="box" pos="-2.42425489 1.45514536 0.214508221" quat="0.582208097 -0.479003459 -0.513790131 -0.40940091" size="0.226987948 0.152846357 0.134736038" rgba="0.234806538 0.623373747 0.34515056 1" />
    <geom name="Floor_001_009" type="box" pos="-1.94005227 2.21659112 0.280651897" quat="0.656532824 -0.655747056 0.223743439 -0.298159987" size="0.245388821 0.224101166 0.164107607" rgba="0.234806538 0.623373747 0.34515056 1" />
    <geom name="Floor_001_010" type="box" pos="-2.31979465 0.115532279 0.320927411" quat="0.576361656 -0.46918276 -0.550032437 -0.380971342" size="0.31480956 0.213481243 0.176715628" rgba="0.505277038 0.0545665249 0.173904255 1" />
    <geom name="Floor_002_001" type="box" pos="-5.24413919 5.43388033 0.62551111" quat="0 0.707106829 0.707106829 0" size="2.89633654 2.3886257 0.0681491112" rgba="0.800007463 0.783353686 0.451678276 1" />
    <geom name="Floor_002_002" type="box" pos="-4.56253099 6.97613859 1.06396449" quat="0.0566424429 -0.732350171 -0.111020185 -0.669424772" size="0.339471594 0.30540487 0.210845111" rgba="0.0762999579 0.0191840585 0.531663537 1" />
    <geom name="Floor_002_003" type="box" pos="-3.43266034 4.95484829 0.818395078" quat="0.614636421 0.632666409 0.351755172 0.313406438" size="0.267827582 0.214931757 0.185821647" rgba="0.0762999579 0.0191840585 0.531663537 1" />
    <geom name="Floor_003_001" type="box" pos="-9.97262669 -0.866540253 1.26455092" quat="0 0.707106829 0.707106829 0" size="7.30361716 2.38862586 0.0681491112" rgba="0.800007463 0.783353686 0.451678276 1" />
    <geom name="Floor_003_002" type="box" pos="-10.0848675 3.30184245 1.62158442" quat="0.183017299 -0.711786687 -0.140590325 -0.663399398" size="0.339043533 0.257887196 0.176036684" rgba="0.423859417 0.601138115 0.12627995 1" />
    <geom name="Floor_003_003" type="box" pos="-11.4322777 -1.32191849 1.5315522" quat="0.583930969 -0.5755409 -0.421789378 0.38713178" size="0.324799782 0.289615564 0.161845584" rgba="0.45167309 0.623394787 0.221228525 1" />
    <geom name="Floor_003_004" type="box" pos="-12.2902718 -1.05758643 1.6024698" quat="0.256362408 0.681610107 0.208713859 -0.652782142" size="0.326076018 0.311719571 0.126524278" rgba="0.505277038 0.0545665249 0.173904255 1" />
    <geom name="Floor_003_005" type="box" pos="-9.45721436 -3.98456144 1.60438883" quat="0.706398547 0.621934831 -0.23547186 -0.24238652" size="0.190594048 0.184327882 0.131994618" rgba="0.623373747 0.216404259 0.245138064 1" />
    <geom name="Floor_003_006" type="box" pos="-10.2433748 -5.64463139 1.47472322" quat="0.539541781 -0.564463854 -0.499347061 0.375403672" size="0.261261001 0.216186405 0.104436989" rgba="0.45167309 0.623394787 0.221228525 1" />
    <geom name="Floor_003_007" type="box" pos="-7.85277367 -4.85616493 1.56678569" quat="0.6446141 0.700601578 -0.188330412 -0.241167679" size="0.300657045 0.275593782 0.149212703" rgba="0.423859417 0.601138115 0.12627995 1" />
    <geom name="Floor_004_001" type="box" pos="-7.10472965 6.13112545 2.23626685" quat="1 0 0 0" size="4.66935238 2.41541646 0.0681490366" rgba="0.800007463 0.783353686 0.451678276 1" />
    <geom name="Floor_004_002" type="box" pos="-11.2185211 5.86329031 2.56365156" quat="0.686270952 -0.7157951 0.0817657858 -0.0999198854" size="0.313456366 0.312994513 0.104934476" rgba="0.623321593 0.252233952 0.114999712 1" />
    <geom name="Floor_004_003" type="box" pos="-9.93017578 5.89826822 2.6566267" quat="0.050631579 0.964162469 0.249170899 0.0757697299" size="0.319205928 0.315613516 0.296442739" rgba="0.623321593 0.252233952 0.114999712 1" />
    <geom name="Floor_004_004" type="box" pos="-6.74836302 4.80564737 2.49905705" quat="0.154980466 0.72949791 0.0641789734 -0.663095057" size="0.28941243 0.238247711 0.169995366" rgba="0.0762999579 0.0191840585 0.531663537 1" />
    <geom name="Floor_004_005" type="box" pos="-4.61318398 6.31012392 2.41218376" quat="0.0445444994 -0.954617977 -0.2895706 0.0535651632" size="0.23782555 0.223074165 0.184380383" rgba="0.234806538 0.623373747 0.34515056 1" />
    <geom name="Stairs_001_001" type="box" pos="-9.83114147 0.834686279 1.35996974" quat="1 0 0 0" size="0.796172571 0.125837481 0.0410223307" rgba="0.234806538 0.623373747 0.34515056 1" />
    <geom name="Stairs_001_002" type="box" pos="-9.83114147 1.08636129 1.40099216" quat="1 0 0 0" size="0.796172571 0.125837441 0.0820446614" rgba="0.623373747 0.216404259 0.245138064 1" />
    <geom name="Stairs_001_003" type="box" pos="-9.83114147 1.33803618 1.44201446" quat="1 0 0 0" size="0.796172571 0.125837522 0.123066992" rgba="0.0725907683 0.623321593 0.510010302 1" />
    <geom name="Stairs_001_004" type="box" pos="-9.83114147 1.58971119 1.48303676" quat="0.707106829 0.707106829 0 0" size="0.796172571 0.164089307 0.125837428" rgba="0.0725907683 0.623321593 0.510010302 1" />
    <geom name="Stairs_001_005" type="box" pos="-9.83114147 1.84138608 1.52405894" quat="0.707106829 0.707106829 0 0" size="0.796172571 0.205111552 0.125837591" rgba="0.0725907683 0.623321593 0.510010302 1" />
    <geom name="Stairs_001_006" type="box" pos="-9.83114147 2.09306121 1.56508136" quat="0.707106829 0.707106829 0 0" size="0.796172571 0.246133879 0.12583751" rgba="0.234806538 0.623373747 0.34515056 1" />
    <geom name="Stairs_001_007" type="box" pos="-9.83114147 2.34473634 1.60610366" quat="0.707106829 0.707106829 0 0" size="0.796172571 0.287156206 0.125837428" rgba="0.0762999579 0.0191840585 0.531663537 1" />
    <geom name="Stairs_001_008" type="box" pos="-9.83114147 2.59641147 1.64712608" quat="0.707106829 0.707106829 0 0" size="0.796172571 0.328178533 0.125837428" rgba="0.623373747 0.216404259 0.245138064 1" />
    <geom name="Stairs_001_009" type="box" pos="-9.83114147 2.84808636 1.68814826" quat="0.707106829 0.707106829 0 0" size="0.796172571 0.369200859 0.12583751" rgba="0.234806538 0.623373747 0.34515056 1" />
    <geom name="Stairs_001_010" type="box" pos="-9.83114147 3.09976101 1.7291708" quat="0.707106829 0.707106829 0 0" size="0.796172571 0.410223186 0.125837428" rgba="0.234806538 0.623373747 0.34515056 1" />
    <geom name="Stairs_001_011" type="box" pos="-9.83114147 3.35143638 1.77019298" quat="0.707106829 0.707106829 0 0" size="0.796172571 0.451245513 0.125837428" rgba="0.0762999579 0.0191840585 0.531663537 1" />
    <geom name="Stairs_001_012" type="box" pos="-9.83114147 3.60311103 1.8112154" quat="0.707106829 0.707106829 0 0" size="0.796172571 0.49226784 0.125837591" rgba="0.0725907683 0.623321593 0.510010302 1" />
    <geom name="Stairs_002_001" type="box" pos="-5.56923866 3.59865713 0.719005585" quat="0.707106829 0 0 0.707106709" size="0.796172734 0.0875147194 0.0261642176" rgba="0.623321593 0.252233952 0.114999712 1" />
    <geom name="Stairs_002_002" type="box" pos="-5.74426842 3.59865713 0.745169818" quat="0.707106829 0 0 0.707106709" size="0.796172734 0.0875147194 0.0523284352" rgba="0.623373747 0.216404259 0.245138064 1" />
    <geom name="Stairs_002_003" type="box" pos="-5.9192977 3.59865713 0.771334052" quat="0.707106829 0 0 0.707106709" size="0.796172734 0.0875147194 0.0784926529" rgba="0.505277038 0.0545665249 0.173904255 1" />
    <geom name="Stairs_002_004" type="box" pos="-6.09432697 3.59865737 0.797498226" quat="0.5 0.50000006 0.5 0.5" size="0.796172734 0.104656862 0.0875147135" rgba="0.0725907683 0.623321593 0.510010302 1" />
    <geom name="Stairs_002_005" type="box" pos="-6.26935673 3.59865737 0.82366246" quat="0.5 0.50000006 0.5 0.5" size="0.796172734 0.130821078 0.0875147418" rgba="0.423859417 0.601138115 0.12627995 1" />
    <geom name="Stairs_002_006" type="box" pos="-6.44438601 3.59865737 0.849826694" quat="0.5 0.50000006 0.5 0.5" size="0.796172734 0.156985293 0.0875147135" rgba="0.423859417 0.601138115 0.12627995 1" />
    <geom name="Stairs_002_007" type="box" pos="-6.61941528 3.59865737 0.875990868" quat="0.5 0.50000006 0.5 0.5" size="0.796172734 0.183149457 0.08751477" rgba="0.623373747 0.216404259 0.245138064 1" />
    <geom name="Stairs_002_008" type="box" pos="-6.79444504 3.59865737 0.902155101" quat="0.5 0.50000006 0.5 0.5" size="0.796172734 0.209313673 0.08751477" rgba="0.505277038 0.0545665249 0.173904255 1" />
    <geom name="Stairs_002_009" type="box" pos="-6.96947432 3.59865737 0.928319335" quat="0.5 0.50000006 0.5 0.5" size="0.796172734 0.235477888 0.08751477" rgba="0.0762999579 0.0191840585 0.531663537 1" />
    <geom name="Stairs_002_010" type="box" pos="-7.14450312 3.59865737 0.954483569" quat="0.5 0.50000006 0.5 0.5" size="0.796172734 0.261642104 0.08751477" rgba="0.0762999579 0.0191840585 0.531663537 1" />
    <geom name="Stairs_002_011" type="box" pos="-7.31953287 3.59865737 0.980647743" quat="0.5 0.50000006 0.5 0.5" size="0.796172734 0.287806319 0.08751477" rgba="0.505277038 0.0545665249 0.173904255 1" />
    <geom name="Stairs_002_012" type="box" pos="-7.49456263 3.59865737 1.00681198" quat="0.5 0.50000006 0.5 0.5" size="0.796172734 0.313970535 0.08751477" rgba="0.234806538 0.623373747 0.34515056 1" />
    <geom name="Stairs_003_001" type="box" pos="-5.2661376 0.82319051 0.0981775969" quat="1 0 0 0" size="0.796172571 0.0903489088 0.0309405081" rgba="0.234806538 0.623373747 0.34515056 1" />
    <geom name="Stairs_003_002" type="box" pos="-5.2661376 1.00388837 0.1291181" quat="1 0 0 0" size="0.796172571 0.0903489574 0.0618810225" rgba="0.505277038 0.0545665249 0.173904255 1" />
    <geom name="Stairs_003_003" type="box" pos="-5.2661376 1.18458605 0.160058618" quat="1 0 0 0" size="0.796172571 0.0903489088 0.0928215369" rgba="0.505277038 0.0545665249 0.173904255 1" />
    <geom name="Stairs_003_004" type="box" pos="-5.2661376 1.36528397 0.19099912" quat="0.707106829 0.707106829 0 0" size="0.796172571 0.12376204 0.0903489007" rgba="0.0725907683 0.623321593 0.510010302 1" />
    <geom name="Stairs_003_005" type="box" pos="-5.2661376 1.54598188 0.221939638" quat="0.707106829 0.707106829 0 0" size="0.796172571 0.154702547 0.0903489007" rgba="0.0725907683 0.623321593 0.510010302 1" />
    <geom name="Stairs_003_006" type="box" pos="-5.2661376 1.7266798 0.252880186" quat="0.707106829 0.707106829 0 0" size="0.796172571 0.185643066 0.0903489007" rgba="0.505277038 0.0545665249 0.173904255 1" />
    <geom name="Stairs_003_007" type="box" pos="-5.2661376 1.9073776 0.283820659" quat="0.707106829 0.707106829 0 0" size="0.796172571 0.21658356 0.0903489007" rgba="0.234806538 0.623373747 0.34515056 1" />
    <geom name="Stairs_003_008" type="box" pos="-5.2661376 2.08807564 0.314761192" quat="0.707106829 0.707106829 0 0" size="0.796172571 0.24752408 0.0903489979" rgba="0.45167309 0.623394787 0.221228525 1" />
    <geom name="Stairs_003_009" type="box" pos="-5.2661376 2.26877356 0.345701724" quat="0.707106829 0.707106829 0 0" size="0.796172571 0.278464599 0.0903488035" rgba="0.234806538 0.623373747 0.34515056 1" />
    <geom name="Stairs_003_010" type="box" pos="-5.2661376 2.44947124 0.376642197" quat="0.707106829 0.707106829 0 0" size="0.796172571 0.309405093 0.0903489979" rgba="0.234806538 0.623373747 0.34515056 1" />
    <geom name="Stairs_004_001" type="box" pos="-3.61671019 -0.337745041 0.0953648165" quat="1 0 0 0" size="0.796172571 0.1372773 0.0281277363" rgba="0.45167309 0.623394787 0.221228525 1" />
    <geom name="Stairs_004_002" type="box" pos="-3.61671019 -0.0631904304 0.123492546" quat="1 0 0 0" size="0.796172571 0.1372773 0.0562554727" rgba="0.45167309 0.623394787 0.221228525 1" />
    <geom name="Stairs_004_003" type="box" pos="-3.61671019 0.211364239 0.151620284" quat="1 0 0 0" size="0.796172571 0.137277321 0.0843832026" rgba="0.623373747 0.216404259 0.245138064 1" />
    <geom name="Stairs_004_004" type="box" pos="-3.61671019 0.48591873 0.179748043" quat="0.707106829 0.707106829 0 0" size="0.796172571 0.112510941 0.137277328" rgba="0.234806538 0.623373747 0.34515056 1" />
    <geom name="Stairs_004_005" type="box" pos="-3.61671019 0.76047343 0.207875744" quat="0.707106829 0.707106829 0 0" size="0.796172571 0.14063867 0.137277328" rgba="0.234806538 0.623373747 0.34515056 1" />
    <geom name="Stairs_004_006" type="box" pos="-3.61671019 1.03502798 0.236003488" quat="0.707106829 0.707106829 0 0" size="0.796172571 0.168766411 0.137277328" rgba="0.234806538 0.623373747 0.34515056 1" />
    <geom name="Stairs_004_007" type="box" pos="-3.61671019 1.30958259 0.264131218" quat="0.707106829 0.707106829 0 0" size="0.796172571 0.196894165 0.137277328" rgba="0.0725907683 0.623321593 0.510010302 1" />
    <geom name="Stairs_004_008" type="box" pos="-3.61671019 1.58413708 0.292258948" quat="0.707106829 0.707106829 0 0" size="0.796172571 0.225021882 0.137277328" rgba="0.505277038 0.0545665249 0.173904255 1" />
    <geom name="Stairs_004_009" type="box" pos="-3.61671019 1.85869181 0.320386678" quat="0.707106829 0.707106829 0 0" size="0.796172571 0.253149636 0.137277328" rgba="0.45167309 0.623394787 0.221228525 1" />
    <geom name="Stairs_004_010" type="box" pos="-3.61671019 2.13324618 0.348514408" quat="0.707106829 0.707106829 0 0" size="0.796172571 0.281277339 0.137277246" rgba="0.423859417 0.601138115 0.12627995 1" />
    <geom name="Stairs_004_011" type="box" pos="-3.61671019 2.40780091 0.376642138" quat="0.707106829 0.707106829 0 0" size="0.796172571 0.309405093 0.137277165" rgba="0.45167309 0.623394787 0.221228525 1" />
  </worldbody>
  <visual>
    <headlight ambient="0.32 0.32 0.32" diffuse="0.55 0.55 0.55" specular="0.08 0.08 0.08" />
    <rgba haze="0.12 0.14 0.16 1" />
  </visual>
</mujoco>